{"meta":{"version":"2.7.16.2","build":1577681044},"pods":{"2700":{"id":2700,"name":"user","label":"User","description":"","type":"user","storage":"meta","object":"user","alias":"","fields":{"gallery":{"id":2701,"name":"gallery","label":"Gallery","description":"","help":"","class":"","type":"wysiwyg","weight":0,"pick_object":"","pick_val":"","sister_id":"","_elementor_controls_usage":[],"required":"0","wysiwyg_editor":"tinymce","wysiwyg_media_buttons":"1","wysiwyg_oembed":"1","wysiwyg_wptexturize":"1","wysiwyg_convert_chars":"1","wysiwyg_wpautop":"1","wysiwyg_allow_shortcode":"1","pick_post_status":["publish"],"admin_only":"0","restrict_role":"0","restrict_capability":"0","hidden":"0","read_only":"0","roles_allowed":["administrator"],"rest_read":"0","rest_write":"0","rest_pick_response":"array","rest_pick_depth":"2","unique":"0","wysiwyg_repeatable":"0","wysiwyg_allowed_html_tags":""},"videos":{"id":2715,"name":"videos","label":"Videos","description":"","help":"","class":"","type":"wysiwyg","weight":1,"pick_object":"","pick_val":"","sister_id":"","_elementor_controls_usage":[],"required":"0","wysiwyg_editor":"tinymce","wysiwyg_media_buttons":"1","wysiwyg_oembed":"0","wysiwyg_wptexturize":"1","wysiwyg_convert_chars":"1","wysiwyg_wpautop":"1","wysiwyg_allow_shortcode":"0","pick_post_status":["publish"],"admin_only":"0","restrict_role":"0","restrict_capability":"0","hidden":"0","read_only":"0","roles_allowed":["administrator"],"rest_read":"0","rest_write":"0","rest_pick_response":"array","rest_pick_depth":"2","wysiwyg_repeatable":0,"wysiwyg_allowed_html_tags":""}},"show_in_menu":1,"_elementor_controls_usage":[],"rest_enable":"0","read_all":"0","write_all":"0"}}}